README.md
README.rst
setup.py
scripts/showdata
scripts/showdata-bak
showdata/__init__.py
showdata/notebook.py
showdata/server.py
showdata/showdata.py
showdata.egg-info/PKG-INFO
showdata.egg-info/SOURCES.txt
showdata.egg-info/dependency_links.txt
showdata.egg-info/requires.txt
showdata.egg-info/top_level.txt
showdata/static/template.html