Metadata-Version: 2.1
Name: showdata
Version: 1.4.9
Summary: Remote file system visualizer and manager.
Home-page: https://github.com/silverbulletmdc/showdata
Author: Dechao Meng
Author-email: dechao.meng@vipl.ict.ac.cn
License: UNKNOWN
Platform: UNKNOWN
